best403unlocker.conf
best403unlocker_py/__init__.py
best403unlocker_py/best403unlocker.conf
best403unlocker_py/cli.py
best403unlocker_py/main.py
LICENSE
README.md
best403unlocker_py-0.1.6.dist-info/entry_points.txt
best403unlocker_py-0.1.6.dist-info/LICENSE
best403unlocker_py-0.1.6.dist-info/METADATA
best403unlocker_py-0.1.6.dist-info/WHEEL
best403unlocker_py-0.1.6.dist-info/RECORD
