Metadata-Version: 2.1
Name: best403unlocker_py
Version: 0.1.6
Summary: python lib of best403unlocker
Home-page: https://github.com/msnemp/best403unlocker-py
License: MIT
Keywords: security,403,bypass,web,penetration-testing
Author: Muhammad sadegh nemat pour
Author-email: mohamadnematpoor@gmail.com
Requires-Python: >=3.9,<4.0
Classifier: Development Status :: 4 - Beta
Classifier: Intended Audience :: Developers
Classifier: License :: OSI Approved :: MIT License
Classifier: Operating System :: OS Independent
Classifier: Programming Language :: Python :: 3
Classifier: Programming Language :: Python :: 3.9
Classifier: Programming Language :: Python :: 3.10
Classifier: Programming Language :: Python :: 3.11
Classifier: Programming Language :: Python :: 3.12
Classifier: Topic :: Security
Classifier: Topic :: Software Development :: Libraries :: Python Modules
Requires-Dist: click (>=8.1.7,<9.0.0)
Requires-Dist: dnspython (>=2.7.0,<3.0.0)
Requires-Dist: pytest (>=8.3.3,<9.0.0)
Requires-Dist: requests (>=2.32.3,<3.0.0)
Requires-Dist: tqdm (>=4.67.1,<5.0.0)
Requires-Dist: typing-extensions (>=4.9.0,<5.0.0)
Project-URL: Bug Tracker, https://github.com/msnemp/best403unlocker-py/issues
Project-URL: Changelog, https://github.com/msnemp/best403unlocker-py/blob/main/CHANGELOG.md
Project-URL: Documentation, https://github.com/msnemp/best403unlocker-py#readme
Project-URL: Repository, https://github.com/msnemp/best403unlocker-py
